flowrs-1.2.1.dist-info/METADATA
flowrs-1.2.1.dist-info/WHEEL
flowrs/__init__.py
flowrs/__init__.pyi
flowrs/py.typed
flowrs/flowrs.abi3.so
flowrs-1.2.1.dist-info/RECORD
