Metadata-Version: 2.4
Name: flowrs
Version: 1.2.1
Summary: A Python module for task orchestration and automation, implemented in Rust.
License: MIT
